setup.py
bitiverse/__init__.py
bitiverse/cointools.py
bitiverse/content.py
bitiverse/generator.py
bitiverse/image_writer.py
bitiverse/messaging.py
bitiverse/ownership.py
bitiverse/pixelwriter.py
bitiverse/pycoin_writer.py
bitiverse/reader.py
bitiverse.egg-info/PKG-INFO
bitiverse.egg-info/SOURCES.txt
bitiverse.egg-info/dependency_links.txt
bitiverse.egg-info/not-zip-safe
bitiverse.egg-info/requires.txt
bitiverse.egg-info/top_level.txt