Metadata-Version: 1.0
Name: bitiverse
Version: 0.1.3
Summary: A Decentralized Web Page
Home-page: www.bitiverse.com
Author: Andrew Barisser
Author-email: UNKNOWN
License: MIT
Platform: UNKNOWN
